LICENSE
gwcloud_python/__init__.py
gwcloud_python/bilby_job.py
gwcloud_python/event_id.py
gwcloud_python/exceptions.py
gwcloud_python/gwcloud.py
gwcloud_python/settings.py
gwcloud_python/tests/__init__.py
gwcloud_python/tests/test_bilby_job.py
gwcloud_python/tests/test_gwcloud_python.py
gwcloud_python/utils/__init__.py
gwcloud_python/utils/file_download.py
gwcloud_python/utils/file_filters.py
gwcloud_python/utils/file_upload.py
gwcloud_python/utils/identifiers.py
gwcloud_python/utils/tests/__init__.py
gwcloud_python/utils/tests/test_file_download.py
gwcloud_python/utils/tests/test_file_filters.py
gwcloud_python/utils/tests/test_file_upload.py
gwcloud_python/utils/tests/test_identifiers.py
gwcloud_python-2.0.0.dist-info/LICENSE
gwcloud_python-2.0.0.dist-info/METADATA
gwcloud_python-2.0.0.dist-info/WHEEL
gwcloud_python-2.0.0.dist-info/RECORD
