Metadata-Version: 2.1
Name: gwcloud-python
Version: 2.0.0
Summary: Wrapper of GWDC API, used for interacting with the GWCloud endpoints
Home-page: https://github.com/gravitationalwavedc/gwcloud_python
License: MIT
Author: Thomas Reichardt
Author-email: treichardt@swin.edu.au
Requires-Python: >=3.7,<4.0
Classifier: License :: OSI Approved :: MIT License
Classifier: Programming Language :: Python :: 3
Classifier: Programming Language :: Python :: 3.7
Classifier: Programming Language :: Python :: 3.8
Classifier: Programming Language :: Python :: 3.9
Classifier: Programming Language :: Python :: 3.10
Classifier: Programming Language :: Python :: 3.11
Classifier: Programming Language :: Python :: 3.12
Provides-Extra: docs
Requires-Dist: Sphinx (>=5.1.1,<6.0.0) ; extra == "docs"
Requires-Dist: graphene-file-upload (>=1.3.0,<2.0.0)
Requires-Dist: gwdc-python (>=1.0,<2.0)
Requires-Dist: importlib-metadata (>=4.12.0,<5.0.0)
Requires-Dist: jwt (>=1.3.1,<2.0.0)
Requires-Dist: requests (>=2.28.1,<3.0.0)
Requires-Dist: sphinx-rtd-theme (>=1.0.0,<2.0.0) ; extra == "docs"
Requires-Dist: tqdm (>=4.64.0,<5.0.0)
Project-URL: Documentation, https://gwcloud-python.readthedocs.io/en/latest/
Project-URL: Repository, https://github.com/gravitationalwavedc/gwcloud_python
